cortex_axon/__init__.py
cortex_axon/agentversion.py
cortex_axon/axon_client.py
cortex_axon/handler.py
generated/__init__.py
generated/__init__.pyi
generated/common_pb2.py
generated/common_pb2.pyi
generated/common_pb2_grpc.py
generated/cortex_api_pb2.py
generated/cortex_api_pb2.pyi
generated/cortex_api_pb2_grpc.py
generated/cortex_axon_agent_pb2.py
generated/cortex_axon_agent_pb2.pyi
generated/cortex_axon_agent_pb2_grpc.py
cortex_axon_sdk-0.0.4.dist-info/METADATA
cortex_axon_sdk-0.0.4.dist-info/WHEEL
cortex_axon_sdk-0.0.4.dist-info/entry_points.txt
cortex_axon_sdk-0.0.4.dist-info/RECORD
