Metadata-Version: 2.3
Name: cortex-axon-sdk
Version: 0.0.4
Summary: Cortex Axon Python SDK
Author: Cortex
Author-email: TODO@cortex.io
Requires-Python: >=3.9,<4.0
Classifier: Programming Language :: Python :: 3
Classifier: Programming Language :: Python :: 3.9
Classifier: Programming Language :: Python :: 3.10
Classifier: Programming Language :: Python :: 3.11
Classifier: Programming Language :: Python :: 3.12
Classifier: Programming Language :: Python :: 3.13
Requires-Dist: grpcio (>=1.68.1,<1.69.0)
Requires-Dist: grpcio-tools (>=1.68.1,<1.69.0)
Requires-Dist: protoletariat (>=3.3.2,<3.4.0)
